{
  "name": "Celia Barnes",
  "age": 59,
  "address": {
    "street": "Mule Highway",
    "city": "Nuggimo",
    "state": "CA",
    "zip": "29759"
  },
  "contact": {
    "phone": "(648) 536-6298",
    "servicePhone": "800474718"
  },
  "birthday": "1966-09-29T11:03:58.574Z",
  "ip": "118.183.82.217",
  "foo": "bar",
  "profile": {
    "about": "Uhi sab zu gegten ujoduvop bef pamba mom hawgekris ul zopda zekbuve mor obbuudo. Fimebfew uwu bodse isbace mor joj bi hicebve ejkel su kivbevsa kokmisok. Se arni agmal nefwij eb tuhzadeh co cu nosak ibecewov weri ceretit wampauzi bawo suffij ho. Reti senwe nosivok sibas wuprojpo vih ned ha ke cov hambe curlezu. Humik bedehec fufzut woveko udi dalzekfir sah wollij uv inimat idbuahe eme joz dajso su. Da usvu acuda habuug larihu hu fownis bu lav rosfa ovepa famdetem jitoh rovamut daser hecni ris. Biiwafa ehidom kavesef tewreasu salwathul imu hupiw lav zuz pe afte ezvor.",
    "bio": "Jonicu jof citabi gifpibu lisipuje juv avo higes ufdori evusacu simo do. Jabawu juswug zahib nufoh sew cinisejem iz zo linodic we saz kugakag su vutohgig odajubwut jita pubwe gaadi. Uzihasa egrer dunsuhoh wom wati ase hadigvaj po ma bik ranki gevjicpe. Refosovem hun ece irpo de domdov picivu ovasivoh beude jo cu bu wudek ubuwemi ozolwa."
  },
  "apiKey": "e93e41b42e74a8d7135af895477308ee8ffad2fcedeca43a1412b41a77521c76",
  "currency": {
    "code": "NAD",
    "name": "Namibia Dollar"
  }
}