{
  "name": "Lida Sparks",
  "age": 27,
  "address": {
    "street": "Panof Terrace",
    "city": "Zezicka",
    "state": "NJ",
    "zip": "62562"
  },
  "contact": {
    "phone": "(270) 578-9786",
    "servicePhone": "800517497"
  },
  "birthday": "1971-11-14T18:31:24.813Z",
  "ip": "165.206.200.101",
  "foo": "bar",
  "profile": {
    "about": "Rijkejefa da conmobfe holipsot zergu rebuti beovokob vin owahi tipudur kejmad hatlij tajpu jihi mozzu ge vo hup. Gafivgac soecu ca cu zoki jajrir tiwobvup kekih ki dohotce cepde fa netminopo nunjiven ofour. Vul heasca vaki nov piwlima acola maztudva ru ehan wob dokoena ipihus oltup uwponji. Kan zemol ekpujkiw jihrabow cakotak balharzo ivrime toro japfo af riecsa jahupa ow joahuwa do fik tas soj. Zikzorhe jiwmut vazok corlemu ero halgowmu no uwifupfab ma gak belkag hodima omdukov obgow ekofumuz. Utise ziniw cilete folgec edanej cuso ona pa utu pu je za vozfozcel futco cutnirjak li dezoca umi.",
    "bio": "Sofmeje howuzud ropjaklev dudgar bevsaka ticpeb amuwipi lijoneg muaw tonef jaus olekova jatoj. Sewow ihfieti re jizhiken juzev utohera azlov hennuted ab vu ab befiwi uhe mi hod vuwesigo. Lil at wamebser kum pugrimuc rezapumo elkilu lovoali pe peg odidod ijiujihi ta weciv hag lugkical."
  },
  "apiKey": "490ccf4045dded65d28f2a3030f70bb33e4eedd63f52376a60a040021944bf5d",
  "currency": {
    "code": "GTQ",
    "name": "Guatemala Quetzal"
  }
}